torch_optstate/__init__.py
torch_optstate/codecs/__init__.py
torch_optstate/codecs/base.py
torch_optstate/codecs/fp32.py
torch_optstate/codecs/lowbit.py
torch_optstate/core/state_store.py
torch_optstate/low_memory.py
torch_optstate/policy/__init__.py
torch_optstate/policy/auto.py
torch_optstate/policy/base.py
torch_optstate/policy/configurable.py
torch_optstate/policy/simple.py
torch_optstate/utils/__init__.py
torch_optstate/utils/gradient_checkpointing.py
torch_optstate/wrap.py
torch_optstate-0.1.1.dist-info/METADATA
torch_optstate-0.1.1.dist-info/WHEEL
torch_optstate-0.1.1.dist-info/licenses/LICENSE
torch_optstate-0.1.1.dist-info/RECORD
