Metadata-Version: 2.4
Name: torch-optstate
Version: 0.1.1
Summary: Optimizer state virtualization and compression for PyTorch
License-File: LICENSE
Author: Vidhu Mathur
Author-email: vidhumathur2002@gmail.com
Requires-Python: >=3.10,<3.15
Classifier: Programming Language :: Python :: 3
Classifier: Programming Language :: Python :: 3.10
Classifier: Programming Language :: Python :: 3.11
Classifier: Programming Language :: Python :: 3.12
Classifier: Programming Language :: Python :: 3.13
Classifier: Programming Language :: Python :: 3.14
Provides-Extra: triton
Requires-Dist: torch (>=2.1.0)
Requires-Dist: triton (>=3.5.1) ; (platform_system == "Linux") and (extra == "triton")
